{
    "id": 60803,
    "parent": 49883,
    "superparent": 9,
    "author": 214,
    "type": "item",
    "subtype": "game",
    "subsubtype": "compo",
    "published": "2017-12-04T00:19:09Z",
    "created": "2017-12-02T02:19:41Z",
    "modified": "2017-12-05T08:12:41Z",
    "version": 195100,
    "slug": "being-plundered",
    "name": "Being Plundered",
    "body": "![mini2.png](ludum-dare/40/being-plundered/images/a90f.png)\n\nIn *Being Plundered*, you are a hard-working asteroid miner who dreams of rich life. Yet every time you get closer to your dreams, those damn space pirates show up and force you to spend your money on repairs.\n\nReach your dream goal of $100000 by mining asteroids and selling the ore, but watch out for the pirates!\nThe more ore and money you have, the more pirates there will be!\n\n**WEBGL BUILD**: https://bradur.github.io/LD40/\n\n## Keys\n### Everywhere\n| Key(s)        | Action        |\n| ------------- |:-------------:|\n| Arrows / WASD | Movement      | \n| Esc / Z       | Pause         |\n| Alt / B       | Toggle radar  |\n| P             | Toggle music  |\n| O             | Toggle sfx    |\n\n### Only outside the space station\n| Key(s)        | Action        |\n| ------------- |:-------------:|\n| Space / Q     | Shoot cannon  | \n| Ctrl /  E     | Fire laser    |\n\n### Only in a shop\n| Key(s)        | Action        |\n| ------------- |:-------------:|\n| Enter         | Buy / Sell    | \n\n## Tips\n- Use the laser on an asteroid. The asteroid will blow up eventually, netting you some ore!\n- When away from the space station, the green arrow points towards it\n- A good way to kite the pirates is to go backwards and shoot\n- Fire the laser AND the cannon at the same time when fighting pirates!\n- Use the radar!\n- Moving in the space station doesn't consume fuel\n- Pirates cannot into space (station)\n\n## Build info\n- I have only tested the WebGL & Windows builds\n\n## Tools\n- Unity3D & Visual Studio Community\n- LMMS for music & sfx\n- Paint.NET\n\n## Screenshots\n![Warping in](ludum-dare/40/being-plundered/images/a81a.png)\n\n![Pirates Galore](ludum-dare/40/being-plundered/images/a817.png)\n\n![Mining](ludum-dare/40/being-plundered/images/a85d.png)\n\n",
    "meta": {
        "author": [
            214
        ],
        "cover": "///content/6d/z/a80e.png",
        "link-01": "https://github.com/bradur/LD40",
        "link-02": "https://bradur.github.io/LD40/",
        "link-02-tag": "42336",
        "link-03": "https://github.com/bradur/LD40/releases/download/Compo/BeingPlundered_Windows_LD40.zip",
        "link-03-tag": "42337",
        "link-04": "https://github.com/bradur/LD40/releases/download/Compo/BeingPlundered_Mac_LD40.app.zip",
        "link-04-tag": "42339",
        "link-05": "https://github.com/bradur/LD40/releases/download/Compo/BeingPlundered_Linux_LD40.zip",
        "link-05-tag": "42341",
        "allow-anonymous-comments": "1"
    },
    "path": "/events/ludum-dare/40/being-plundered",
    "parents": [
        1,
        5,
        9,
        49883
    ],
    "love": 0,
    "notes": 32,
    "notes-timestamp": "2017-12-28T11:55:31Z",
    "grade": {
        "grade-01": 44,
        "grade-02": 44,
        "grade-03": 44,
        "grade-04": 44,
        "grade-05": 44,
        "grade-06": 43,
        "grade-07": 36,
        "grade-08": 42
    },
    "magic": {
        "cool": 95.38919802105,
        "feedback": 46,
        "given": 37.875,
        "grade": 42.625,
        "grade-01-average": 3.881,
        "grade-01-result": 72,
        "grade-02-average": 3.774,
        "grade-02-result": 106,
        "grade-03-average": 3.357,
        "grade-03-result": 248,
        "grade-04-average": 3.643,
        "grade-04-result": 236,
        "grade-05-average": 3.857,
        "grade-05-result": 131,
        "grade-06-average": 3.988,
        "grade-06-result": 27,
        "grade-07-average": 2.632,
        "grade-07-result": 341,
        "grade-08-average": 3.738,
        "grade-08-result": 63,
        "smart": 18.127705166035
    },
    "eventName": "Ludum Dare 40",
    "cover": "ludum-dare/40/being-plundered/images/a80e.png",
    "url": "games\\ludum-dare\\40\\being-plundered"
}